intensity_logger/__init__.py
intensity_logger/logger.py
intensity_logger-0.1.2.dist-info/LICENSE
intensity_logger-0.1.2.dist-info/METADATA
intensity_logger-0.1.2.dist-info/WHEEL
intensity_logger-0.1.2.dist-info/top_level.txt
intensity_logger-0.1.2.dist-info/RECORD
