Metadata-Version: 2.1
Name: intensity-logger
Version: 0.1.2
Summary: A logging utility for Python applications with customizable intensity
Home-page: https://github.com/idkconsole/intensity-logger
Author: idkconsole, eagledev1337, homicide3301
Author-email: idkconsole@proton.me
Keywords: logging logger intensity color logs
Classifier: Development Status :: 3 - Alpha
Classifier: Intended Audience :: Developers
Classifier: Topic :: Software Development :: Libraries
Classifier: License :: OSI Approved :: MIT License
Classifier: Programming Language :: Python :: 3
Classifier: Programming Language :: Python :: 3.6
Classifier: Programming Language :: Python :: 3.7
Classifier: Programming Language :: Python :: 3.8
Classifier: Programming Language :: Python :: 3.9
Classifier: Programming Language :: Python :: 3.10
Classifier: Operating System :: OS Independent
Requires-Python: >=3.6
License-File: LICENSE
